gpt_manifold/__init__.py
gpt_manifold/__main__.py
gpt_manifold/gpt_manifold.py
gpt_manifold/logger.py
gpt_manifold/strings.py
gpt_manifold-1.1.1.dist-info/LICENSE
gpt_manifold-1.1.1.dist-info/METADATA
gpt_manifold-1.1.1.dist-info/WHEEL
gpt_manifold-1.1.1.dist-info/top_level.txt
gpt_manifold-1.1.1.dist-info/RECORD
