Metadata-Version: 2.1
Name: gpt-manifold
Version: 1.1.1
Summary: An assistant for betting on prediction markets on manifold.markets, utilizing OpenAI's GPT APIs.
Home-page: https://github.com/minosvasilias/gpt-manifold
Author: Markus Sobkowski
Author-email: sobmarski@gmail.com
Classifier: License :: OSI Approved :: MIT License
Classifier: Programming Language :: Python :: 3
Classifier: Programming Language :: Python :: 3.6
Classifier: Programming Language :: Python :: 3.7
Classifier: Programming Language :: Python :: 3.8
Classifier: Programming Language :: Python :: 3.9
License-File: LICENSE
Requires-Dist: openai
Requires-Dist: pick
